dbt_buddy/__init__.py
dbt_buddy/cli/__init__.py
dbt_buddy/cli/cli.py
dbt_buddy/document/__init__.py
dbt_buddy/document/cli.py
dbt_buddy/document/doc_generator/__init__.py
dbt_buddy/document/doc_generator/constants.py
dbt_buddy/document/doc_generator/generator.py
dbt_buddy-0.1.0.dist-info/METADATA
dbt_buddy-0.1.0.dist-info/WHEEL
dbt_buddy-0.1.0.dist-info/entry_points.txt
dbt_buddy-0.1.0.dist-info/licenses/LICENSE
dbt_buddy-0.1.0.dist-info/RECORD
