Metadata-Version: 2.1
Name: dbt-buddy
Version: 0.1.0
Summary: AI-based documentation for dbt-models
Author-email: Egor Popov <Egor.POPOV@uni.rest>
License-File: LICENSE
Keywords: AI-documentation,LLM,YandexGPT,dbt
Requires-Python: >=3.9
Requires-Dist: click<8.1.4,>=7.0
Requires-Dist: dbt-core<1.7,>1.6
Requires-Dist: dbt-postgres<1.7,>1.6
Requires-Dist: pyfiglet<1.0.0
Requires-Dist: python-dotenv==1.0.1
Requires-Dist: yandex-cloud-ml-sdk>=0.13.1
Provides-Extra: dev
Requires-Dist: pre-commit>=3.7.0; extra == 'dev'
